AudioFusion/__init__.py
AudioFusion/__main__.py
AudioFusion/async/__init__.py
AudioFusion/async/__main__.py
AudioFusion-0.1.5.dist-info/License
AudioFusion-0.1.5.dist-info/METADATA
AudioFusion-0.1.5.dist-info/WHEEL
AudioFusion-0.1.5.dist-info/top_level.txt
AudioFusion-0.1.5.dist-info/RECORD
