Metadata-Version: 2.1
Name: AudioFusion
Version: 0.1.5
Summary: Enhance your music experience – effortlessly add immersive 8D, slowed, and reverb effects to any song.
Home-page: https://github.com/MineisZarox/AudioFusion
Author: Zarox
Author-email: mineiszarox@gmail.com
License: MIT
Project-URL: Bug Tracker, https://github.com/MineisZarox/AudioFusion
Keywords: music,reverb,slowed,8d,editor,python
Classifier: Programming Language :: Python :: 3
Classifier: License :: OSI Approved :: MIT License
Classifier: Operating System :: OS Independent
Requires-Python: >=3.8
License-File: License
Requires-Dist: pydub
Requires-Dist: SoundFile
Requires-Dist: pedalboard
